compas_dem/__init__.py
compas_dem/__main__.py
compas_dem/analysis/__init__.py
compas_dem/analysis/cra.py
compas_dem/analysis/fea.py
compas_dem/elements/__init__.py
compas_dem/elements/block.py
compas_dem/interactions/__init__.py
compas_dem/interactions/contact.py
compas_dem/models/__init__.py
compas_dem/models/blockmodel.py
compas_dem/notebook/__init__.py
compas_dem/notebook/buffers.py
compas_dem/notebook/modelobject.py
compas_dem/templates/__init__.py
compas_dem/templates/arch.py
compas_dem/templates/barrel.py
compas_dem/templates/dome.py
compas_dem/templates/template.py
compas_dem/templates/wall.py
compas_dem/viewer/__init__.py
compas_dem/viewer/viewer.py
compas_dem-0.4.2.dist-info/licenses/LICENSE
compas_dem-0.4.2.dist-info/METADATA
compas_dem-0.4.2.dist-info/WHEEL
compas_dem-0.4.2.dist-info/top_level.txt
compas_dem-0.4.2.dist-info/RECORD
