Metadata-Version: 2.4
Name: compas_dem
Version: 0.4.2
Summary: Discrete Element Models for Modern Masonry Design and Historic Masonry Assessment
Author-email: tom van mele <tom.v.mele@gmail.com>
License: MIT License
Project-URL: Homepage, https://blockresearchgroup.github.io/compas_dem
Project-URL: Documentation, https://blockresearchgroup.github.io/compas_dem
Project-URL: Repository, https://github.com/blockresearchgroup/compas_dem
Project-URL: Changelog, https://github.com/blockresearchgroup/compas_dem/blob/main/CHANGELOG.md
Project-URL: Issues, https://github.com/blockresearchgroup/compas_dem/issues
Project-URL: Forum, https://forum.compas-framework.org/
Classifier: Development Status :: 4 - Beta
Classifier: Topic :: Scientific/Engineering
Classifier: Operating System :: Unix
Classifier: Operating System :: POSIX
Classifier: Operating System :: Microsoft :: Windows
Classifier: Programming Language :: Python
Classifier: Programming Language :: Python :: 3
Classifier: Programming Language :: Python :: 3.10
Classifier: Programming Language :: Python :: 3.11
Classifier: Programming Language :: Python :: 3.12
Requires-Python: >=3.9
License-File: LICENSE
Requires-Dist: compas>=2.4
Requires-Dist: compas_cgal>=0.9.1
Requires-Dist: compas_libigl>=0.7.4
Requires-Dist: compas_model>=0.9.1
Provides-Extra: dev
Requires-Dist: attrs>=17.4; extra == "dev"
Requires-Dist: bump-my-version; extra == "dev"
Requires-Dist: compas_invocations2>=0.4.0; extra == "dev"
Requires-Dist: invoke>=0.14; extra == "dev"
Requires-Dist: ruff; extra == "dev"
Requires-Dist: sphinx_compas2_theme; extra == "dev"
Requires-Dist: twine; extra == "dev"
Requires-Dist: wheel; extra == "dev"
Provides-Extra: viz
Requires-Dist: compas_notebook; extra == "viz"
Requires-Dist: compas_viewer; extra == "viz"
Provides-Extra: analysis
Requires-Dist: compas_assembly; extra == "analysis"
Requires-Dist: compas_cra; extra == "analysis"
Requires-Dist: compas_gmsh; extra == "analysis"
Dynamic: license-file
